[{
  "id": 1,
  "name": "Roda Maudlin",
  "email": "rmaudlin0@123-reg.co.uk",
  "gender": "Non-binary",
  "country": "Poland",
  "phone": "279-728-4874",
  "img": "https://robohash.org/corruptiducimusut.jpg?size=250x250&set=set1",
  "salary": 110
}, {
  "id": 2,
  "name": "Salmon Fletcher",
  "email": "sfletcher1@cbc.ca",
  "gender": "Polygender",
  "country": "Russia",
  "phone": "547-463-3612",
  "img": "https://robohash.org/nesciuntdolorvero.jpg?size=250x250&set=set1",
  "salary": 734
}, {
  "id": 3,
  "name": "Bondie Mateiko",
  "email": "bmateiko2@trellian.com",
  "gender": "Non-binary",
  "country": "Philippines",
  "phone": "171-115-1342",
  "img": "https://robohash.org/ideteos.jpg?size=250x250&set=set1",
  "salary": 222
}, {
  "id": 4,
  "name": "Emelita Crewe",
  "email": "ecrewe3@ehow.com",
  "gender": "Genderfluid",
  "country": "China",
  "phone": "865-225-1030",
  "img": "https://robohash.org/voluptatemsaepedelectus.jpg?size=250x250&set=set1",
  "salary": 344
}, {
  "id": 5,
  "name": "Julian Teese",
  "email": "jteese4@bloglines.com",
  "gender": "Genderfluid",
  "country": "Armenia",
  "phone": "942-315-9744",
  "img": "https://robohash.org/aperiamnisinam.jpg?size=250x250&set=set1",
  "salary": 221
}, {
  "id": 6,
  "name": "Annalee Matthiesen",
  "email": "amatthiesen5@posterous.com",
  "gender": "Non-binary",
  "country": "Thailand",
  "phone": "784-586-6460",
  "img": "https://robohash.org/molestiaererumaut.jpg?size=250x250&set=set1",
  "salary": 232
}, {
  "id": 7,
  "name": "Martainn Keymer",
  "email": "mkeymer6@edublogs.org",
  "gender": "Polygender",
  "country": "China",
  "phone": "203-792-0773",
  "img": "https://robohash.org/praesentiumsedratione.jpg?size=250x250&set=set1",
  "salary": 323
}, {
  "id": 8,
  "name": "Berta Dakhov",
  "email": "bdakhov7@abc.net.au",
  "gender": "Agender",
  "country": "Brazil",
  "phone": "345-676-9511",
  "img": "https://robohash.org/molestiaemaximebeatae.jpg?size=250x250&set=set1",
  "salary": 691
}, {
  "id": 9,
  "name": "Wallie Karpets",
  "email": "wkarpets8@gmpg.org",
  "gender": "Genderfluid",
  "country": "China",
  "phone": "627-840-6196",
  "img": "https://robohash.org/errorconsecteturrepellendus.jpg?size=250x250&set=set1",
  "salary": 222
}, {
  "id": 10,
  "name": "Maurie Hasker",
  "email": "mhasker9@jiathis.com",
  "gender": "Male",
  "country": "Panama",
  "phone": "247-548-3165",
  "img": "https://robohash.org/veritatismolestiasvelit.jpg?size=250x250&set=set1",
  "salary": 470
}, {
  "id": 11,
  "name": "Mikael Klimus",
  "email": "mklimusa@fotki.com",
  "gender": "Bigender",
  "country": "Portugal",
  "phone": "719-917-2096",
  "img": "https://robohash.org/pariaturfacilisdignissimos.jpg?size=250x250&set=set1",
  "salary": 222
}, {
  "id": 12,
  "name": "Shaine Drinan",
  "email": "sdrinanb@pinterest.com",
  "gender": "Polygender",
  "country": "Somalia",
  "phone": "452-214-6277",
  "img": "https://robohash.org/aspernaturculpadolore.jpg?size=250x250&set=set1",
  "salary": 100
}, {
  "id": 13,
  "name": "Norrie Le Prevost",
  "email": "nlec@addtoany.com",
  "gender": "Bigender",
  "country": "China",
  "phone": "638-689-4287",
  "img": "https://robohash.org/dolorquotempora.jpg?size=250x250&set=set1",
  "salary": 211
}, {
  "id": 14,
  "name": "Alie Barrus",
  "email": "abarrusd@slashdot.org",
  "gender": "Agender",
  "country": "Croatia",
  "phone": "388-879-9803",
  "img": "https://robohash.org/molestiaeminussit.jpg?size=250x250&set=set1",
  "salary": 212
}, {
  "id": 15,
  "name": "Hermy Lidington",
  "email": "hlidingtone@economist.com",
  "gender": "Male",
  "country": "France",
  "phone": "805-504-4953",
  "img": "https://robohash.org/iustoteneturrem.jpg?size=250x250&set=set1",
  "salary": 112
}]